.assembly extern '.library'
{
	.ver 0:0:0:0
}
.assembly '<Assembly>'
{
	.ver 0:0:0:0
}
.module '<Module>'
.namespace 'System'
{
.class public auto ansi 'Test' extends ['.library']'System'.'Object'
{
.method public hidebysig specialname rtspecialname instance void '.ctor'() cil managed java 
{
	aload_0
	invokespecial	instance void ['.library']'System'.'Object'::'.ctor'()
	return
	.locals 1
	.maxstack 1
} // method .ctor
} // class Test
} // namespace System
.namespace 'System'
{
.class public auto interface abstract ansi 'ITest'
{
} // class ITest
} // namespace System
.namespace 'System'
{
.class public auto ansi 'Test1`1'<'T'> extends ['.library']'System'.'Object'
{
.method public hidebysig specialname rtspecialname instance void '.ctor'() cil managed java 
{
	aload_0
	invokespecial	instance void ['.library']'System'.'Object'::'.ctor'()
	return
	.locals 1
	.maxstack 1
} // method .ctor
} // class Test1`1
} // namespace System
.namespace 'System'
{
.class public auto ansi 'Test2`1'<.ctor valuetype 'T'> extends ['.library']'System'.'Object'
{
.method public hidebysig specialname rtspecialname instance void '.ctor'() cil managed java 
{
	aload_0
	invokespecial	instance void ['.library']'System'.'Object'::'.ctor'()
	return
	.locals 1
	.maxstack 1
} // method .ctor
} // class Test2`1
} // namespace System
.namespace 'System'
{
.class public auto ansi 'Test3`1'<class 'T'> extends ['.library']'System'.'Object'
{
.method public hidebysig specialname rtspecialname instance void '.ctor'() cil managed java 
{
	aload_0
	invokespecial	instance void ['.library']'System'.'Object'::'.ctor'()
	return
	.locals 1
	.maxstack 1
} // method .ctor
} // class Test3`1
} // namespace System
.namespace 'System'
{
.class public auto ansi 'Test4`1'<(class 'System'.'Test')'T'> extends ['.library']'System'.'Object'
{
.method public hidebysig specialname rtspecialname instance void '.ctor'() cil managed java 
{
	aload_0
	invokespecial	instance void ['.library']'System'.'Object'::'.ctor'()
	return
	.locals 1
	.maxstack 1
} // method .ctor
} // class Test4`1
} // namespace System
.namespace 'System'
{
.class public auto ansi 'Test5`1'<(class 'System'.'Test', class 'System'.'ITest')'T'> extends ['.library']'System'.'Object'
{
.method public hidebysig specialname rtspecialname instance void '.ctor'() cil managed java 
{
	aload_0
	invokespecial	instance void ['.library']'System'.'Object'::'.ctor'()
	return
	.locals 1
	.maxstack 1
} // method .ctor
} // class Test5`1
} // namespace System
